nostrclient/__init__.py
nostrclient/__version__.py
nostrclient/actions.py
nostrclient/bech32.py
nostrclient/event.py
nostrclient/key.py
nostrclient/localStorage.py
nostrclient/log.py
nostrclient/nip19.py
nostrclient/relay.py
nostrclient/relay_pool.py
nostrclient/subscription.py
nostrclient/user.py
nostrclient-1.0.5.dist-info/LICENSE
nostrclient-1.0.5.dist-info/METADATA
nostrclient-1.0.5.dist-info/WHEEL
nostrclient-1.0.5.dist-info/top_level.txt
nostrclient-1.0.5.dist-info/RECORD
