Metadata-Version: 2.1
Name: nostrclient
Version: 1.0.5
Author: duozhu
Project-URL: Home, https://github.com/duozhutuan/nostrclient
License-File: LICENSE
Requires-Dist: cryptography >=37.0.4
Requires-Dist: secp256k1 >=0.14.0
Requires-Dist: websocket-client >=1.3.3
